foobar/ex.py
mutation-0.4.8.dist-info/LICENSE
mutation-0.4.8.dist-info/METADATA
mutation-0.4.8.dist-info/WHEEL
mutation-0.4.8.dist-info/top_level.txt
mutation-0.4.8.dist-info/RECORD
