Metadata-Version: 2.1
Name: mutation
Version: 0.4.8
Summary: Mutation testing made easy
Requires-Python: >=3.10
License-File: LICENSE
